{"apifoxProject":"1.0.0","info":{"name":"cms-tem","description":"","mockRule":{"rules":[],"enableSystemRule":true}},"apiCollection":[{"name":"根目录","auth":{},"parentId":0,"serverId":"","description":"","identityPattern":{"httpApi":{"type":"methodAndPath","bodyType":"","fields":[]}},"preProcessors":[{"id":"inheritProcessors","type":"inheritProcessors","data":{}}],"postProcessors":[{"id":"inheritProcessors","type":"inheritProcessors","data":{}}],"inheritPostProcessors":{},"inheritPreProcessors":{},"items":[{"name":"系统管理","auth":{},"parentId":0,"serverId":"","description":"","identityPattern":{"httpApi":{"type":"inherit","bodyType":"","fields":[]}},"preProcessors":[{"id":"inheritProcessors","type":"inheritProcessors","data":{}}],"postProcessors":[{"id":"inheritProcessors","type":"inheritProcessors","data":{}}],"inheritPostProcessors":{},"inheritPreProcessors":{},"items":[{"name":"登录管理","auth":{},"parentId":26416076,"serverId":"","description":"","identityPattern":{"httpApi":{"type":"inherit","bodyType":"","fields":[]}},"preProcessors":[{"id":"inheritProcessors","type":"inheritProcessors","data":{}}],"postProcessors":[{"id":"inheritProcessors","type":"inheritProcessors","data":{}}],"inheritPostProcessors":{},"inheritPreProcessors":{},"items":[{"name":"用户登录","api":{"id":"134140621","method":"post","path":"/login","parameters":{},"auth":{},"commonParameters":{"query":[],"body":[],"cookie":[],"header":[]},"responses":[{"id":"371139786","name":"成功","code":200,"contentType":"json","jsonSchema":{"type":"object","properties":{}}}],"responseExamples":[],"requestBody":{"type":"application/json","parameters":[],"jsonSchema":{"title":"用户登录","type":"object","properties":{"username":{"type":"string","title":"用户名"},"password":{"type":"string","title":"用户密码"}},"x-apifox-orders":["username","password"],"required":["username","password"]}},"description":"","tags":[],"status":"developing","serverId":"","operationId":"","sourceUrl":"","ordering":10,"cases":[{"id":128731243,"type":"http","path":null,"name":"已登录","responseId":371139786,"parameters":{},"commonParameters":{"query":[],"body":[],"header":[],"cookie":[]},"requestBody":{"parameters":[],"type":"application/json","data":"{\r\n    \"username\": \"superadmin\",\r\n    \"password\": \"123456\"\r\n}"},"auth":{},"advancedSettings":{},"preProcessors":[],"postProcessors":[{"type":"customScript","data":"const res =pm.response.json();\r\npm.environment.set(\"token\", res.data.token);\r\n\r\n","enable":true}],"inheritPostProcessors":{},"inheritPreProcessors":{}}],"mocks":[],"customApiFields":"{}","advancedSettings":{},"mockScript":{},"codeSamples":[],"commonResponseStatus":{},"responseChildren":[],"preProcessors":[],"postProcessors":[],"inheritPostProcessors":{},"inheritPreProcessors":{}}}]},{"name":"用户管理","auth":{},"parentId":26416076,"serverId":"","description":"","identityPattern":{"httpApi":{"type":"inherit","bodyType":"","fields":[]}},"preProcessors":[{"id":"inheritProcessors","type":"inheritProcessors","data":{}}],"postProcessors":[{"id":"inheritProcessors","type":"inheritProcessors","data":{}}],"inheritPostProcessors":{},"inheritPreProcessors":{},"items":[{"name":"添加用户","api":{"id":"134106619","method":"post","path":"/user/","parameters":{},"auth":{"type":"bearer","bearer":{"token":"{{token}}"}},"commonParameters":{"query":[],"body":[],"cookie":[],"header":[]},"responses":[{"id":"371072340","name":"成功","code":200,"contentType":"json","jsonSchema":{"type":"object","properties":{}}}],"responseExamples":[],"requestBody":{"type":"application/json","parameters":[],"jsonSchema":{"title":"添加用户","description":"添加用户请求参数","type":"object","properties":{"username":{"type":"string","title":"用户名"},"password":{"type":"string","title":"用户密码"},"nickname":{"type":"string","title":"用户昵称"},"email":{"type":["string","null"],"title":"用户邮箱"},"intro":{"type":["string","null"],"title":"用户备注"},"telephone":{"title":"用户号码","type":["string","null"]},"roleId":{"title":"绑定角色id","type":["number","null"]},"departmentId":{"type":["number","null"],"title":"部门id"},"state":{"type":"number","enum":[1,0],"x-apifox":{"enumDescriptions":{"0":"禁用","1":"启用"}},"default":1,"title":"用户状态"}},"x-apifox-orders":["username","password","state","nickname","telephone","email","intro","roleId","departmentId"],"required":["username","password","nickname","telephone","email","state","intro","roleId","departmentId"]}},"description":"","tags":[],"status":"developing","serverId":"","operationId":"","sourceUrl":"","ordering":10,"cases":[{"id":128713148,"type":"http","path":null,"name":"成功","responseId":371072340,"parameters":{},"commonParameters":{"query":[],"body":[],"header":[],"cookie":[]},"requestBody":{"parameters":[],"type":"application/json","data":"{\r\n    \"username\": \"testuser\",\r\n    \"password\": \"123456\",\r\n    \"nickname\": \"测试昵称\",\r\n    \"telephone\": \"18128226636\",\r\n    \"email\": \"o.dsfwgn@qq.com\",\r\n    \"intro\": null,\r\n    \"roleId\": null,\r\n    \"departmentId\": null\r\n}"},"auth":{"type":"bearer","bearer":{"token":"{{token}}"}},"advancedSettings":{},"preProcessors":[],"postProcessors":[],"inheritPostProcessors":{},"inheritPreProcessors":{}}],"mocks":[],"customApiFields":"{}","advancedSettings":{},"mockScript":{},"codeSamples":[],"commonResponseStatus":{},"responseChildren":[],"preProcessors":[],"postProcessors":[],"inheritPostProcessors":{},"inheritPreProcessors":{}}},{"name":"编辑用户","api":{"id":"139214732","method":"patch","path":"/user/{id}","parameters":{"path":[{"name":"id","required":true,"id":"id#0"}]},"auth":{"type":"bearer","bearer":{"token":"{{token}}"}},"commonParameters":{"query":[],"body":[],"cookie":[],"header":[]},"responses":[{"id":"39695843","name":"成功","code":200,"contentType":"json","jsonSchema":{"type":"object","properties":{}}}],"responseExamples":[],"requestBody":{"type":"application/json","parameters":[],"jsonSchema":{"title":"添加用户","description":"添加用户请求参数","type":"object","properties":{"username":{"type":"string","title":"用户名"},"password":{"type":"string","title":"用户密码"},"nickname":{"type":"string","title":"用户昵称"},"email":{"type":["string","null"],"title":"用户邮箱"},"intro":{"type":["string","null"],"title":"用户备注"},"telephone":{"title":"用户号码","type":["string","null"]},"roleId":{"title":"绑定角色id","type":["number","null"]},"departmentId":{"type":["number","null"],"title":"部门id"},"state":{"type":"number","enum":[1,0],"x-apifox":{"enumDescriptions":{"0":"禁用","1":"启用"}},"default":1,"title":"用户状态"}},"x-apifox-orders":["username","password","state","nickname","telephone","email","intro","roleId","departmentId"],"required":["username","password","nickname","telephone","email","state","intro","roleId","departmentId"]}},"description":"","tags":[],"status":"developing","serverId":"","operationId":"","sourceUrl":"","ordering":11,"cases":[{"id":132846829,"type":"http","path":null,"name":"成功","responseId":39695843,"parameters":{},"commonParameters":{"query":[],"body":[],"header":[],"cookie":[]},"requestBody":{"parameters":[],"type":"application/json","data":"{\r\n    \"username\": \"testuser\",\r\n    \"password\": \"123456\",\r\n    \"nickname\": \"测试昵称\",\r\n    \"telephone\": \"18128226636\",\r\n    \"email\": \"o.dsfwgn@qq.com\",\r\n    \"intro\": null,\r\n    \"roleId\": null,\r\n    \"departmentId\": null\r\n}"},"auth":{"type":"bearer","bearer":{"token":"{{token}}"}},"advancedSettings":{},"preProcessors":[],"postProcessors":[],"inheritPostProcessors":{},"inheritPreProcessors":{}}],"mocks":[],"customApiFields":"{}","advancedSettings":{},"mockScript":{},"codeSamples":[],"commonResponseStatus":{},"responseChildren":[],"preProcessors":[],"postProcessors":[],"inheritPostProcessors":{},"inheritPreProcessors":{}}},{"name":"查询用户列表","api":{"id":"134222577","method":"get","path":"/user/","parameters":{"query":[{"required":false,"description":"分页尺寸","type":"string","name":"pageSize","id":"6dkAT520IM","example":"10"},{"required":false,"description":"分页页码","type":"string","name":"page","id":"ezUt9pwEaY","example":"1"},{"required":false,"description":"用户名","type":"string","name":"username","id":"Kz7TAlUBKd","example":""},{"required":false,"description":"用户昵称","type":"string","name":"nickname","id":"214rZBK221"},{"required":false,"description":"用户电话","type":"string","name":"telephone","id":"HtI3spaKUa"},{"required":false,"description":"用户状态， 1：启用，0：禁用","type":"number","name":"state","id":"L53gTUWpqY","example":"1"},{"required":false,"description":"创建时间范围的开始时间","type":"string","name":"startTime","id":"JsW73yQozm"},{"required":false,"description":"创建时间范围的结束时间","type":"string","name":"endTime","id":"Dth6LLi0Ny"}]},"auth":{"type":"bearer","bearer":{"token":"{{token}}"}},"commonParameters":{"query":[],"body":[],"cookie":[],"header":[]},"responses":[{"id":"371276430","name":"成功","code":200,"contentType":"json","jsonSchema":{"type":"object","properties":{}}}],"responseExamples":[],"requestBody":{"type":"application/json","parameters":[],"jsonSchema":{"title":"添加用户","description":"添加用户请求参数","type":"object","properties":{},"x-apifox-orders":[]}},"description":"","tags":[],"status":"developing","serverId":"","operationId":"","sourceUrl":"","ordering":12,"cases":[],"mocks":[],"customApiFields":"{}","advancedSettings":{},"mockScript":{},"codeSamples":[],"commonResponseStatus":{},"responseChildren":[],"preProcessors":[],"postProcessors":[],"inheritPostProcessors":{},"inheritPreProcessors":{}}},{"name":"查询用户详情","api":{"id":"134246706","method":"get","path":"/user/{id}","parameters":{"query":[],"path":[{"name":"id","required":true,"id":"id#0"}]},"auth":{"type":"bearer","bearer":{"token":"{{token}}"}},"commonParameters":{"query":[],"body":[],"cookie":[],"header":[]},"responses":[{"id":"371334535","name":"成功","code":200,"contentType":"json","jsonSchema":{"type":"object","properties":{}}}],"responseExamples":[],"requestBody":{"type":"application/json","parameters":[],"jsonSchema":{"title":"添加用户","description":"添加用户请求参数","type":"object","properties":{},"x-apifox-orders":[]}},"description":"通过用户id获取用户信息","tags":[],"status":"developing","serverId":"","operationId":"","sourceUrl":"","ordering":24,"cases":[],"mocks":[],"customApiFields":"{}","advancedSettings":{},"mockScript":{},"codeSamples":[],"commonResponseStatus":{},"responseChildren":[],"preProcessors":[],"postProcessors":[],"inheritPostProcessors":{},"inheritPreProcessors":{}}},{"name":"获取用户信息","api":{"id":"135099137","method":"get","path":"/user/info","parameters":{"query":[],"path":[]},"auth":{"type":"bearer","bearer":{"token":"{{token}}"}},"commonParameters":{"query":[],"body":[],"cookie":[],"header":[]},"responses":[{"id":"37926182","name":"成功","code":200,"contentType":"json","jsonSchema":{"type":"object","properties":{}}}],"responseExamples":[],"requestBody":{"type":"application/json","parameters":[],"jsonSchema":{"title":"添加用户","description":"添加用户请求参数","type":"object","properties":{},"x-apifox-orders":[]}},"description":"通过token获取用户信息","tags":[],"status":"developing","serverId":"","operationId":"","sourceUrl":"","ordering":30,"cases":[],"mocks":[],"customApiFields":"{}","advancedSettings":{},"mockScript":{},"codeSamples":[],"commonResponseStatus":{},"responseChildren":[],"preProcessors":[],"postProcessors":[],"inheritPostProcessors":{},"inheritPreProcessors":{}}},{"name":"删除用户","api":{"id":"134153299","method":"delete","path":"/user/{id}","parameters":{"path":[{"name":"id","required":true,"id":"id#0"}]},"auth":{"type":"bearer","bearer":{"token":"{{token}}"}},"commonParameters":{"query":[],"body":[],"cookie":[],"header":[]},"responses":[{"id":"371159939","name":"成功","code":200,"contentType":"json","jsonSchema":{"type":"object","properties":{}}}],"responseExamples":[],"requestBody":{"type":"none","parameters":[]},"description":"","tags":[],"status":"developing","serverId":"","operationId":"","sourceUrl":"","ordering":36,"cases":[],"mocks":[],"customApiFields":"{}","advancedSettings":{},"mockScript":{},"codeSamples":[],"commonResponseStatus":{},"responseChildren":[],"preProcessors":[],"postProcessors":[],"inheritPostProcessors":{},"inheritPreProcessors":{}}}]},{"name":"角色管理","auth":{},"parentId":26416076,"serverId":"","description":"","identityPattern":{"httpApi":{"type":"inherit","bodyType":"","fields":[]}},"preProcessors":[{"id":"inheritProcessors","type":"inheritProcessors","data":{}}],"postProcessors":[{"id":"inheritProcessors","type":"inheritProcessors","data":{}}],"inheritPostProcessors":{},"inheritPreProcessors":{},"items":[{"name":"查询全部未禁用角色列表","api":{"id":"138815993","method":"get","path":"/role/all","parameters":{},"auth":{"type":"bearer","bearer":{"token":"{{token}}"}},"commonParameters":{"query":[],"body":[],"cookie":[],"header":[]},"responses":[{"id":"380515549","name":"成功","code":200,"contentType":"json","jsonSchema":{"type":"object","properties":{}}}],"responseExamples":[],"requestBody":{"type":"none","parameters":[]},"description":"","tags":[],"status":"developing","serverId":"","operationId":"","sourceUrl":"","ordering":10,"cases":[],"mocks":[],"customApiFields":"{}","advancedSettings":{},"mockScript":{},"codeSamples":[],"commonResponseStatus":{},"responseChildren":[],"preProcessors":[],"postProcessors":[],"inheritPostProcessors":{},"inheritPreProcessors":{}}},{"name":"添加角色","api":{"id":"134292272","method":"post","path":"/role/","parameters":{},"auth":{"type":"bearer","bearer":{"token":"{{token}}"}},"commonParameters":{"query":[],"body":[],"cookie":[],"header":[]},"responses":[{"id":"371425491","name":"成功","code":200,"contentType":"json","jsonSchema":{"type":"object","properties":{}}}],"responseExamples":[],"requestBody":{"type":"application/json","parameters":[],"jsonSchema":{"title":"添加角色","description":"添加角色请求参数","type":"object","properties":{"intro":{"title":"角色备注","type":["string","null"]},"roleName":{"type":"string","title":"角色名"},"roleIndex":{"type":"string","title":"角色索引"},"sort":{"title":"角色排序","description":"默认值0","type":"number"},"state":{"title":"角色状态","description":"默认值启用(1)","type":"number","enum":[1,0],"x-apifox":{"enumDescriptions":{"0":"禁用","1":"启用"}},"default":1},"menuList":{"title":"菜单id列表","type":["array","null"],"items":{"type":"number","description":"菜单id"}}},"x-apifox-orders":["roleName","roleIndex","sort","state","intro","menuList"],"required":["roleName","roleIndex","sort","state","menuList","intro"]}},"description":"","tags":[],"status":"developing","serverId":"","operationId":"","sourceUrl":"","ordering":11,"cases":[{"id":128847344,"type":"http","path":null,"name":"成功","responseId":371425491,"parameters":{},"commonParameters":{"query":[],"body":[],"header":[],"cookie":[]},"requestBody":{"parameters":[],"type":"application/json","data":"{\n    \"roleName\": \"测试角色\",\n    \"roleIndex\": \"testRoleIndex\",\n    \"sort\": 0,\n    \"state\": 1,\n    \"menuList\": null,\n    \"intro\": null\n}"},"auth":{"type":"bearer","bearer":{"token":"{{token}}"}},"advancedSettings":{},"preProcessors":[],"postProcessors":[],"inheritPostProcessors":{},"inheritPreProcessors":{}}],"mocks":[],"customApiFields":"{}","advancedSettings":{},"mockScript":{},"codeSamples":[],"commonResponseStatus":{},"responseChildren":[],"preProcessors":[],"postProcessors":[],"inheritPostProcessors":{},"inheritPreProcessors":{}}},{"name":"编辑角色","api":{"id":"139252472","method":"patch","path":"/role/{id}","parameters":{"path":[{"name":"id","required":true,"id":"id#0"}]},"auth":{"type":"bearer","bearer":{"token":"{{token}}"}},"commonParameters":{"query":[],"body":[],"cookie":[],"header":[]},"responses":[{"id":"381537049","name":"成功","code":200,"contentType":"json","jsonSchema":{"type":"object","properties":{}}}],"responseExamples":[],"requestBody":{"type":"application/json","parameters":[],"jsonSchema":{"title":"添加角色","description":"添加角色请求参数","type":"object","properties":{"intro":{"title":"角色备注","type":["string","null"]},"roleName":{"type":"string","title":"角色名"},"roleIndex":{"type":"string","title":"角色索引"},"sort":{"title":"角色排序","description":"默认值0","type":"number"},"state":{"title":"角色状态","description":"默认值启用(1)","type":"number","enum":[1,0],"x-apifox":{"enumDescriptions":{"0":"禁用","1":"启用"}},"default":1},"menuList":{"title":"菜单id列表","type":["array","null"],"items":{"type":"number","description":"菜单id"}}},"x-apifox-orders":["roleName","roleIndex","sort","state","intro","menuList"],"required":["roleName","roleIndex","sort","state","menuList","intro"]}},"description":"","tags":[],"status":"developing","serverId":"","operationId":"","sourceUrl":"","ordering":14,"cases":[{"id":132853225,"type":"http","path":null,"name":"成功","responseId":381537049,"parameters":{"path":[{"id":"id#0","relatedId":"id#0","relatedName":"id","name":"id","value":"1","enable":true}]},"commonParameters":{"query":[],"body":[],"header":[],"cookie":[]},"requestBody":{"parameters":[],"type":"application/json","data":"{\n    \"roleName\": \"测试角色\",\n    \"roleIndex\": \"testRoleIndex\",\n    \"sort\": 0,\n    \"state\": 1,\n    \"menuList\": null,\n    \"intro\": null\n}"},"auth":{"type":"bearer","bearer":{"token":"{{token}}"}},"advancedSettings":{},"preProcessors":[],"postProcessors":[],"inheritPostProcessors":{},"inheritPreProcessors":{}}],"mocks":[],"customApiFields":"{}","advancedSettings":{},"mockScript":{},"codeSamples":[],"commonResponseStatus":{},"responseChildren":[],"preProcessors":[],"postProcessors":[],"inheritPostProcessors":{},"inheritPreProcessors":{}}},{"name":"查询角色列表","api":{"id":"134292273","method":"get","path":"/role/","parameters":{"query":[{"required":false,"description":"分页尺寸","type":"string","name":"pageSize","id":"6dkAT520IM","example":"10"},{"required":false,"description":"分页页码","type":"string","name":"page","id":"ezUt9pwEaY","example":"1"},{"required":false,"description":"角色名称","type":"string","name":"roleName","id":"bIoaCe127d"}]},"auth":{"type":"bearer","bearer":{"token":"{{token}}"}},"commonParameters":{"query":[],"body":[],"cookie":[],"header":[]},"responses":[{"id":"371425492","name":"成功","code":200,"contentType":"json","jsonSchema":{"type":"object","properties":{}}}],"responseExamples":[],"requestBody":{"type":"application/json","parameters":[],"jsonSchema":{"title":"添加用户","description":"添加用户请求参数","type":"object","properties":{},"x-apifox-orders":[]}},"description":"","tags":[],"status":"developing","serverId":"","operationId":"","sourceUrl":"","ordering":18,"cases":[],"mocks":[],"customApiFields":"{}","advancedSettings":{},"mockScript":{},"codeSamples":[],"commonResponseStatus":{},"responseChildren":[],"preProcessors":[],"postProcessors":[],"inheritPostProcessors":{},"inheritPreProcessors":{}}},{"name":"查询角色详情","api":{"id":"134292274","method":"get","path":"/role/{id}","parameters":{"query":[],"path":[{"name":"id","required":true,"id":"id#0"}]},"auth":{"type":"bearer","bearer":{"token":"{{token}}"}},"commonParameters":{"query":[],"body":[],"cookie":[],"header":[]},"responses":[{"id":"371425493","name":"成功","code":200,"contentType":"json","jsonSchema":{"type":"object","properties":{}}}],"responseExamples":[],"requestBody":{"type":"application/json","parameters":[],"jsonSchema":{"title":"添加用户","description":"添加用户请求参数","type":"object","properties":{},"x-apifox-orders":[]}},"description":"","tags":[],"status":"developing","serverId":"","operationId":"","sourceUrl":"","ordering":27,"cases":[],"mocks":[],"customApiFields":"{}","advancedSettings":{},"mockScript":{},"codeSamples":[],"commonResponseStatus":{},"responseChildren":[],"preProcessors":[],"postProcessors":[],"inheritPostProcessors":{},"inheritPreProcessors":{}}},{"name":"通过角色id查询菜单","api":{"id":"135098303","method":"get","path":"/role/{id}/menu","parameters":{"query":[],"path":[{"name":"id","required":true,"id":"id#0"}]},"auth":{"type":"bearer","bearer":{"token":"{{token}}"}},"commonParameters":{"query":[],"body":[],"cookie":[],"header":[]},"responses":[{"id":"373100062","name":"成功","code":200,"contentType":"json","jsonSchema":{"type":"object","properties":{}}}],"responseExamples":[],"requestBody":{"type":"application/json","parameters":[],"jsonSchema":{"title":"添加用户","description":"添加用户请求参数","type":"object","properties":{},"x-apifox-orders":[]}},"description":"","tags":[],"status":"developing","serverId":"","operationId":"","sourceUrl":"","ordering":34,"cases":[],"mocks":[],"customApiFields":"{}","advancedSettings":{},"mockScript":{},"codeSamples":[],"commonResponseStatus":{},"responseChildren":[],"preProcessors":[],"postProcessors":[],"inheritPostProcessors":{},"inheritPreProcessors":{}}},{"name":"通过角色id查询权限列表","api":{"id":"137660244","method":"get","path":"/role/{id}/permission","parameters":{"query":[],"path":[{"name":"id","required":true,"id":"id#0"}]},"auth":{"type":"bearer","bearer":{"token":"{{token}}"}},"commonParameters":{"query":[],"body":[],"cookie":[],"header":[]},"responses":[{"id":"39072349","name":"成功","code":200,"contentType":"json","jsonSchema":{"type":"object","properties":{}}}],"responseExamples":[],"requestBody":{"type":"application/json","parameters":[],"jsonSchema":{"title":"添加用户","description":"添加用户请求参数","type":"object","properties":{},"x-apifox-orders":[]}},"description":"","tags":[],"status":"developing","serverId":"","operationId":"","sourceUrl":"","ordering":38,"cases":[],"mocks":[],"customApiFields":"{}","advancedSettings":{},"mockScript":{},"codeSamples":[],"commonResponseStatus":{},"responseChildren":[],"preProcessors":[],"postProcessors":[],"inheritPostProcessors":{},"inheritPreProcessors":{}}},{"name":"删除角色","api":{"id":"134292276","method":"delete","path":"/role/{id}","parameters":{"path":[{"name":"id","required":true,"id":"id#0"}]},"auth":{"type":"bearer","bearer":{"token":"{{token}}"}},"commonParameters":{"query":[],"body":[],"cookie":[],"header":[]},"responses":[{"id":"371425495","name":"成功","code":200,"contentType":"json","jsonSchema":{"type":"object","properties":{}}}],"responseExamples":[],"requestBody":{"type":"none","parameters":[]},"description":"","tags":[],"status":"developing","serverId":"","operationId":"","sourceUrl":"","ordering":42,"cases":[],"mocks":[],"customApiFields":"{}","advancedSettings":{},"mockScript":{},"codeSamples":[],"commonResponseStatus":{},"responseChildren":[],"preProcessors":[],"postProcessors":[],"inheritPostProcessors":{},"inheritPreProcessors":{}}}]},{"name":"部门管理","auth":{},"parentId":26416076,"serverId":"","description":"","identityPattern":{"httpApi":{"type":"inherit","bodyType":"","fields":[]}},"preProcessors":[{"id":"inheritProcessors","type":"inheritProcessors","data":{}}],"postProcessors":[{"id":"inheritProcessors","type":"inheritProcessors","data":{}}],"inheritPostProcessors":{},"inheritPreProcessors":{},"items":[{"name":"添加部门","api":{"id":"134353856","method":"post","path":"/department/","parameters":{},"auth":{"type":"bearer","bearer":{"token":"{{token}}"}},"commonParameters":{"query":[],"body":[],"cookie":[],"header":[]},"responses":[{"id":"371552110","name":"成功","code":200,"contentType":"json","jsonSchema":{"type":"object","properties":{}}}],"responseExamples":[],"requestBody":{"type":"application/json","parameters":[],"jsonSchema":{"title":"添加角色","description":"添加角色请求参数","type":"object","properties":{"intro":{"type":["string","null"],"title":"部门备注"},"sort":{"title":"角色排序","type":["number","null"],"description":"默认值0"},"state":{"title":"角色状态","type":["number","null"],"description":"默认值启用(1)","enum":[1,0],"x-apifox":{"enumDescriptions":{"0":"禁用","1":"启用"}}},"depName":{"type":"string","title":"角色名"},"parentId":{"type":["number","null"],"title":"父级部门"}},"x-apifox-orders":["depName","sort","state","intro","parentId"],"required":["depName","sort","state","intro","parentId"]}},"description":"","tags":[],"status":"developing","serverId":"","operationId":"","sourceUrl":"","ordering":12,"cases":[{"id":128893684,"type":"http","path":null,"name":"成功","responseId":371552110,"parameters":{},"commonParameters":{"query":[],"body":[],"header":[],"cookie":[]},"requestBody":{"parameters":[],"type":"application/json","data":"{\n    \"depName\": \"音况状头\",\n    \"sort\": 6,\n    \"state\": 1,\n    \"intro\": \"eu officia et anim irure\",\n    \"parentId\": 46\n}"},"auth":{"type":"bearer","bearer":{"token":"{{token}}"}},"advancedSettings":{},"preProcessors":[],"postProcessors":[],"inheritPostProcessors":{},"inheritPreProcessors":{}}],"mocks":[],"customApiFields":"{}","advancedSettings":{},"mockScript":{},"codeSamples":[],"commonResponseStatus":{},"responseChildren":[],"preProcessors":[],"postProcessors":[],"inheritPostProcessors":{},"inheritPreProcessors":{}}},{"name":"编辑部门","api":{"id":"134353857","method":"patch","path":"/department/{id}","parameters":{"path":[{"name":"id","required":true,"id":"id#0"}]},"auth":{"type":"bearer","bearer":{"token":"{{token}}"}},"commonParameters":{"query":[],"body":[],"cookie":[],"header":[]},"responses":[{"id":"371552111","name":"成功","code":200,"contentType":"json","jsonSchema":{"type":"object","properties":{}}}],"responseExamples":[],"requestBody":{"type":"application/json","parameters":[],"jsonSchema":{"title":"编辑部门","type":"object","properties":{"intro":{"type":["string","null"],"title":"部门备注"},"sort":{"title":"排序","type":["number","null"],"description":"默认值0"},"state":{"title":"状态","type":["number","null"],"description":"默认值启用(1)","enum":[1,0],"x-apifox":{"enumDescriptions":{"0":"禁用","1":"启用"}},"default":1},"depName":{"type":"string","title":"部门"},"parentId":{"type":["number","null"],"title":"父id"}},"x-apifox-orders":["depName","sort","state","intro","parentId"],"required":["depName","sort","state","intro","parentId"]}},"description":"","tags":[],"status":"developing","serverId":"","operationId":"","sourceUrl":"","ordering":16,"cases":[{"id":128910597,"type":"http","path":null,"name":"成功","responseId":371552111,"parameters":{"path":[{"id":"id#0","relatedId":"id#0","relatedName":"id","name":"id","value":"6","enable":true}]},"commonParameters":{"query":[],"body":[],"header":[],"cookie":[]},"requestBody":{"parameters":[],"type":"application/json","data":"{\r\n    \"depName\": \"测试部门\",\r\n    \"sort\": 0,\r\n    \"state\": 1,\r\n    \"intro\": null,\r\n    \"parentId\": null\r\n}"},"auth":{"type":"bearer","bearer":{"token":"{{token}}"}},"advancedSettings":{},"preProcessors":[],"postProcessors":[],"inheritPostProcessors":{},"inheritPreProcessors":{}}],"mocks":[],"customApiFields":"{}","advancedSettings":{},"mockScript":{},"codeSamples":[],"commonResponseStatus":{},"responseChildren":[],"preProcessors":[],"postProcessors":[],"inheritPostProcessors":{},"inheritPreProcessors":{}}},{"name":"查询部门列表","api":{"id":"134353858","method":"get","path":"/department/","parameters":{"query":[{"required":false,"description":"部门名称","type":"string","name":"depName","id":"K5YaTeLSe2"}]},"auth":{"type":"bearer","bearer":{"token":"{{token}}"}},"commonParameters":{"query":[],"body":[],"cookie":[],"header":[]},"responses":[{"id":"371552112","name":"成功","code":200,"contentType":"json","jsonSchema":{"type":"object","properties":{}}}],"responseExamples":[],"requestBody":{"type":"application/json","parameters":[],"jsonSchema":{"title":"添加用户","description":"添加用户请求参数","type":"object","properties":{},"x-apifox-orders":[]}},"description":"","tags":[],"status":"developing","serverId":"","operationId":"","sourceUrl":"","ordering":22,"cases":[],"mocks":[],"customApiFields":"{}","advancedSettings":{},"mockScript":{},"codeSamples":[],"commonResponseStatus":{},"responseChildren":[],"preProcessors":[],"postProcessors":[],"inheritPostProcessors":{},"inheritPreProcessors":{}}},{"name":"查询全部未禁用部门列表","api":{"id":"138825486","method":"get","path":"/department/all","parameters":{"query":[]},"auth":{"type":"bearer","bearer":{"token":"{{token}}"}},"commonParameters":{"query":[],"body":[],"cookie":[],"header":[]},"responses":[{"id":"380554094","name":"成功","code":200,"contentType":"json","jsonSchema":{"type":"object","properties":{}}}],"responseExamples":[],"requestBody":{"type":"application/json","parameters":[],"jsonSchema":{"title":"添加用户","description":"添加用户请求参数","type":"object","properties":{},"x-apifox-orders":[]}},"description":"","tags":[],"status":"developing","serverId":"","operationId":"","sourceUrl":"","ordering":28,"cases":[],"mocks":[],"customApiFields":"{}","advancedSettings":{},"mockScript":{},"codeSamples":[],"commonResponseStatus":{},"responseChildren":[],"preProcessors":[],"postProcessors":[],"inheritPostProcessors":{},"inheritPreProcessors":{}}},{"name":"查询部门详情","api":{"id":"134353859","method":"get","path":"/department/{id}","parameters":{"query":[],"path":[{"name":"id","required":true,"id":"id#0"}]},"auth":{"type":"bearer","bearer":{"token":"{{token}}"}},"commonParameters":{"query":[],"body":[],"cookie":[],"header":[]},"responses":[{"id":"371552113","name":"成功","code":200,"contentType":"json","jsonSchema":{"type":"object","properties":{}}}],"responseExamples":[],"requestBody":{"type":"application/json","parameters":[],"jsonSchema":{"title":"添加用户","description":"添加用户请求参数","type":"object","properties":{},"x-apifox-orders":[]}},"description":"","tags":[],"status":"developing","serverId":"","operationId":"","sourceUrl":"","ordering":34,"cases":[],"mocks":[],"customApiFields":"{}","advancedSettings":{},"mockScript":{},"codeSamples":[],"commonResponseStatus":{},"responseChildren":[],"preProcessors":[],"postProcessors":[],"inheritPostProcessors":{},"inheritPreProcessors":{}}},{"name":"删除部门","api":{"id":"134353861","method":"delete","path":"/department/{id}","parameters":{"path":[{"name":"id","required":true,"id":"id#0"}]},"auth":{"type":"bearer","bearer":{"token":"{{token}}"}},"commonParameters":{"query":[],"body":[],"cookie":[],"header":[]},"responses":[{"id":"371552114","name":"成功","code":200,"contentType":"json","jsonSchema":{"type":"object","properties":{}}}],"responseExamples":[],"requestBody":{"type":"none","parameters":[]},"description":"","tags":[],"status":"developing","serverId":"","operationId":"","sourceUrl":"","ordering":48,"cases":[],"mocks":[],"customApiFields":"{}","advancedSettings":{},"mockScript":{},"codeSamples":[],"commonResponseStatus":{},"responseChildren":[],"preProcessors":[],"postProcessors":[],"inheritPostProcessors":{},"inheritPreProcessors":{}}}]},{"name":"菜单管理","auth":{},"parentId":26416076,"serverId":"","description":"","identityPattern":{"httpApi":{"type":"inherit","bodyType":"","fields":[]}},"preProcessors":[{"id":"inheritProcessors","type":"inheritProcessors","data":{}}],"postProcessors":[{"id":"inheritProcessors","type":"inheritProcessors","data":{}}],"inheritPostProcessors":{},"inheritPreProcessors":{},"items":[{"name":"添加菜单","api":{"id":"134750975","method":"post","path":"/menu/","parameters":{},"auth":{"type":"bearer","bearer":{"token":"{{token}}"}},"commonParameters":{"query":[],"body":[],"cookie":[],"header":[]},"responses":[{"id":"372379031","name":"成功","code":200,"contentType":"json","jsonSchema":{"type":"object","properties":{}}}],"responseExamples":[],"requestBody":{"type":"application/json","parameters":[],"jsonSchema":{"title":"添加菜单","type":"object","properties":{"menuName":{"title":"菜单名称","type":"string","description":"可以为空，不能重名"},"url":{"title":"菜单地址","type":"string"},"icon":{"type":["string","null"],"title":"图标","description":"菜单图标"},"sort":{"type":"number","default":0,"title":"排序","description":"通过数值由第到高排序"},"menuType":{"type":"number","enum":[1,2],"x-apifox":{"enumDescriptions":{"1":"菜单类型","2":"枚举类型"}},"default":1,"title":"菜单类型","description":"默认菜单类型"},"isLink":{"type":"number","default":0,"enum":[0,1],"x-apifox":{"enumDescriptions":{"0":"不是外链","1":"外链"}},"title":"是否外链","description":"默认不是外链"},"isIframe":{"type":"number","default":1,"enum":[0,1],"x-apifox":{"enumDescriptions":{"0":"不是内嵌","1":"内嵌"}},"title":"是否内嵌","description":"默认内嵌"},"parentId":{"title":"上级菜单","description":"上级菜单id","type":["number","null"]},"permission":{"title":"权限标识","description":"可以为空，不能重名","type":["string","null"]},"redirectUrl":{"title":"重定向地址","type":["string","null"],"description":"当是一级菜单时可以添加重定向地址"},"link":{"type":"string","title":"菜单地址"}},"x-apifox-orders":["menuName","url","parentId","icon","sort","menuType","isLink","link","isIframe","permission","redirectUrl"],"required":["menuName","url","parentId","icon","sort","menuType","isLink","isIframe","permission","redirectUrl","link"]}},"description":"","tags":[],"status":"developing","serverId":"","operationId":"","sourceUrl":"","ordering":14,"cases":[{"id":129225091,"type":"http","path":null,"name":"成功","responseId":372379031,"parameters":{},"commonParameters":{"query":[],"body":[],"header":[],"cookie":[]},"requestBody":{"parameters":[],"type":"application/json","data":"{\r\n    \"menuName\": \"系统管理\",\r\n    \"url\": \"/main/system\",\r\n    \"state\": 1,\r\n    \"parentId\": null,\r\n    \"icon\": \"\",\r\n    \"sort\": 0,\r\n    \"menuType\": 1,\r\n    \"isLink\": 0,\r\n    \"link\": \"\",\r\n    \"isIframe\": 1,\r\n    \"permission\": \"\",\r\n    \"redirectUrl\": \"\"\r\n}"},"auth":{"type":"bearer","bearer":{"token":"{{token}}"}},"advancedSettings":{},"preProcessors":[],"postProcessors":[],"inheritPostProcessors":{},"inheritPreProcessors":{}}],"mocks":[],"customApiFields":"{}","advancedSettings":{},"mockScript":{},"codeSamples":[],"commonResponseStatus":{},"responseChildren":[],"preProcessors":[],"postProcessors":[],"inheritPostProcessors":{},"inheritPreProcessors":{}}},{"name":"编辑菜单","api":{"id":"139261313","method":"post","path":"/menu/{id}","parameters":{"path":[{"name":"id","required":true,"id":"id#0"}]},"auth":{"type":"bearer","bearer":{"token":"{{token}}"}},"commonParameters":{"query":[],"body":[],"cookie":[],"header":[]},"responses":[{"id":"381549546","name":"成功","code":200,"contentType":"json","jsonSchema":{"type":"object","properties":{}}}],"responseExamples":[],"requestBody":{"type":"application/json","parameters":[],"jsonSchema":{"title":"添加菜单","type":"object","properties":{"menuName":{"title":"菜单名称","type":"string","description":"可以为空，不能重名"},"url":{"title":"菜单地址","type":"string"},"icon":{"type":["string","null"],"title":"图标","description":"菜单图标"},"sort":{"type":"number","default":0,"title":"排序","description":"通过数值由第到高排序"},"menuType":{"type":"number","enum":[1,2],"x-apifox":{"enumDescriptions":{"1":"菜单类型","2":"枚举类型"}},"default":1,"title":"菜单类型","description":"默认菜单类型"},"isLink":{"type":"number","default":0,"enum":[0,1],"x-apifox":{"enumDescriptions":{"0":"不是外链","1":"外链"}},"title":"是否外链","description":"默认不是外链"},"isIframe":{"type":"number","default":1,"enum":[0,1],"x-apifox":{"enumDescriptions":{"0":"不是内嵌","1":"内嵌"}},"title":"是否内嵌","description":"默认内嵌"},"parentId":{"title":"上级菜单","description":"上级菜单id","type":["number","null"]},"permission":{"title":"权限标识","description":"可以为空，不能重名","type":["string","null"]},"redirectUrl":{"title":"重定向地址","type":["string","null"],"description":"当是一级菜单时可以添加重定向地址"},"link":{"type":"string","title":"菜单地址"}},"x-apifox-orders":["menuName","url","parentId","icon","sort","menuType","isLink","link","isIframe","permission","redirectUrl"],"required":["menuName","url","parentId","icon","sort","menuType","isLink","isIframe","permission","redirectUrl","link"]}},"description":"","tags":[],"status":"developing","serverId":"","operationId":"","sourceUrl":"","ordering":21,"cases":[{"id":132858406,"type":"http","path":null,"name":"成功","responseId":381549546,"parameters":{"path":[{"id":"id#0","relatedId":"id#0","relatedName":"id","name":"id","value":"1","enable":true}]},"commonParameters":{"query":[],"body":[],"header":[],"cookie":[]},"requestBody":{"parameters":[],"type":"application/json","data":"{\r\n    \"menuName\": \"系统管理\",\r\n    \"url\": \"/main/system\",\r\n    \"state\": 1,\r\n    \"parentId\": null,\r\n    \"icon\": \"\",\r\n    \"sort\": 0,\r\n    \"menuType\": 1,\r\n    \"isLink\": 0,\r\n    \"link\": \"\",\r\n    \"isIframe\": 1,\r\n    \"permission\": \"\",\r\n    \"redirectUrl\": \"\"\r\n}"},"auth":{"type":"bearer","bearer":{"token":"{{token}}"}},"advancedSettings":{},"preProcessors":[],"postProcessors":[],"inheritPostProcessors":{},"inheritPreProcessors":{}}],"mocks":[],"customApiFields":"{}","advancedSettings":{},"mockScript":{},"codeSamples":[],"commonResponseStatus":{},"responseChildren":[],"preProcessors":[],"postProcessors":[],"inheritPostProcessors":{},"inheritPreProcessors":{}}},{"name":"查询菜单列表","api":{"id":"134750978","method":"get","path":"/menu/","parameters":{"query":[]},"auth":{"type":"bearer","bearer":{"token":"{{token}}"}},"commonParameters":{"query":[],"body":[],"cookie":[],"header":[]},"responses":[{"id":"372383483","name":"成功","code":200,"contentType":"json","jsonSchema":{"type":"object","properties":{}}}],"responseExamples":[],"requestBody":{"type":"application/json","parameters":[],"jsonSchema":{"title":"添加用户","description":"添加用户请求参数","type":"object","properties":{},"x-apifox-orders":[]}},"description":"","tags":[],"status":"developing","serverId":"","operationId":"","sourceUrl":"","ordering":28,"cases":[],"mocks":[],"customApiFields":"{}","advancedSettings":{},"mockScript":{},"codeSamples":[],"commonResponseStatus":{},"responseChildren":[],"preProcessors":[],"postProcessors":[],"inheritPostProcessors":{},"inheritPreProcessors":{}}},{"name":"删除菜单","api":{"id":"134750980","method":"delete","path":"/menu/{id}","parameters":{"path":[{"name":"id","required":true,"id":"id#0"}]},"auth":{"type":"bearer","bearer":{"token":"{{token}}"}},"commonParameters":{"query":[],"body":[],"cookie":[],"header":[]},"responses":[{"id":"372383485","name":"成功","code":200,"contentType":"json","jsonSchema":{"type":"object","properties":{}}}],"responseExamples":[],"requestBody":{"type":"none","parameters":[]},"description":"","tags":[],"status":"developing","serverId":"","operationId":"","sourceUrl":"","ordering":54,"cases":[],"mocks":[],"customApiFields":"{}","advancedSettings":{},"mockScript":{},"codeSamples":[],"commonResponseStatus":{},"responseChildren":[],"preProcessors":[],"postProcessors":[],"inheritPostProcessors":{},"inheritPreProcessors":{}}}]}]}]}],"socketCollection":[],"docCollection":[],"schemaCollection":[],"responseCollection":[],"apiTestCaseCollection":[{"name":"根目录","children":[],"items":[]}],"apiTestSuiteCollection":[],"testCaseReferences":[],"environments":[],"commonScripts":[],"databaseConnections":[],"globalVariables":[],"commonParameters":null,"projectSetting":{"id":"3197710","auth":{},"servers":[{"id":"default","name":"默认服务"}],"gateway":[],"language":"zh-CN","apiStatuses":["developing","testing","released","deprecated"],"mockSettings":{},"preProcessors":[],"postProcessors":[],"advancedSettings":{},"initialDisabledMockIds":[],"cloudMock":{"security":"free","enable":false,"tokenKey":"apifoxToken"}},"projectAssociations":[]}